run_as_admin/__init__.py
run_as_admin/run_as_admin.py
run_as_admin-1.7.9.dist-info/METADATA
run_as_admin-1.7.9.dist-info/WHEEL
run_as_admin-1.7.9.dist-info/licenses/LICENCE
run_as_admin-1.7.9.dist-info/RECORD
