Metadata-Version: 2.1
Name: run_as_admin
Version: 1.7.9
Summary: This script provides a simple way to execute a file as an administrator on Windows systems.
Project-URL: Homepage, https://github.com/barno1994/runasadmin
Project-URL: Issues, https://github.com/barno1994/runasadmin/issues
Author-email: Barno Chakraborty <barno.baptu@gmail.com>
License-File: LICENCE
Classifier: License :: OSI Approved :: MIT License
Classifier: Operating System :: Microsoft :: Windows
Classifier: Programming Language :: Python :: 3
Requires-Python: >=3.8
